src/__init__.py
src/paginator.py
sa_paginator-0.1.0.dist-info/LICENSE
sa_paginator-0.1.0.dist-info/METADATA
sa_paginator-0.1.0.dist-info/WHEEL
sa_paginator-0.1.0.dist-info/RECORD
